README.md
setup.py
txjsonrpcqueue/__init__.py
txjsonrpcqueue/exception.py
txjsonrpcqueue/rpcforwarder.py
txjsonrpcqueue/wildcardqueue.py
txjsonrpcqueue.egg-info/PKG-INFO
txjsonrpcqueue.egg-info/SOURCES.txt
txjsonrpcqueue.egg-info/dependency_links.txt
txjsonrpcqueue.egg-info/requires.txt
txjsonrpcqueue.egg-info/top_level.txt
txjsonrpcqueue/asyncio/__init__.py
txjsonrpcqueue/asyncio/rpcforwarder.py
txjsonrpcqueue/asyncio/wildcardqueue.py
txjsonrpcqueue/asyncio/steem/__init__.py
txjsonrpcqueue/asyncio/steem/injector.py
txjsonrpcqueue/core/__init__.py
txjsonrpcqueue/core/wildcardqueue.py
txjsonrpcqueue/core/steem/__init__.py
txjsonrpcqueue/core/steem/injector.py
txjsonrpcqueue/steem/__init__.py
txjsonrpcqueue/steem/injector.py